smi_to_ass/__init__.py
smi_to_ass/common.py
smi_to_ass/smi_to_ass.py
smi_to_ass/util.py
smi_to_ass-0.1.0.dist-info/METADATA
smi_to_ass-0.1.0.dist-info/WHEEL
smi_to_ass-0.1.0.dist-info/RECORD
