Metadata-Version: 2.1
Name: smi-to-ass
Version: 0.1.0
Summary: 
Author: luhavis
Author-email: luhavis.dev@gmail.com
Requires-Python: >=3.11,<4.0
Classifier: Programming Language :: Python :: 3
Classifier: Programming Language :: Python :: 3.11
Classifier: Programming Language :: Python :: 3.12
Requires-Dist: beautifulsoup4 (>=4.12.2,<5.0.0)
Requires-Dist: chardet (>=5.2.0,<6.0.0)
